{
    "CARAGUATATUBA - UBATUBA - SAO SEBASTIAO_Agriculture":{
        "CARAGUATATUBA - UBATUBA - SAO SEBASTIAO_Agriculture":0.002002622,
        "CARAGUATATUBA - UBATUBA - SAO SEBASTIAO_Mining":0.001102888,
        "CARAGUATATUBA - UBATUBA - SAO SEBASTIAO_Manufacturing":0.0393833605,
        "CARAGUATATUBA - UBATUBA - SAO SEBASTIAO_Utilities":0.023301242,
        "CARAGUATATUBA - UBATUBA - SAO SEBASTIAO_Construction":0.000592695,
        "CARAGUATATUBA - UBATUBA - SAO SEBASTIAO_Trade":0.059395135,
        "CARAGUATATUBA - UBATUBA - SAO SEBASTIAO_Transport":0.019993629,
        "CARAGUATATUBA - UBATUBA - SAO SEBASTIAO_Business":0.000201581,
        "CARAGUATATUBA - UBATUBA - SAO SEBASTIAO_Financial":0.015253392,
        "CARAGUATATUBA - UBATUBA - SAO SEBASTIAO_RealEstate":0.0000364576,
        "CARAGUATATUBA - UBATUBA - SAO SEBASTIAO_OtherServices":0.00369196,
        "CARAGUATATUBA - UBATUBA - SAO SEBASTIAO_Government":0.00074141,
        "RestBR_Agriculture":0.038531689,
        "RestBR_Mining":0.0,
        "RestBR_Manufacturing":0.1670396695,
        "RestBR_Utilities":0.0,
        "RestBR_Construction":0.0,
        "RestBR_Trade":0.0,
        "RestBR_Transport":0.0,
        "RestBR_Business":0.0,
        "RestBR_Financial":0.0,
        "RestBR_RealEstate":0.0,
        "RestBR_OtherServices":0.0,
        "RestBR_Government":0.0
    },
    "CARAGUATATUBA - UBATUBA - SAO SEBASTIAO_Mining":{
        "CARAGUATATUBA - UBATUBA - SAO SEBASTIAO_Agriculture":0.0000359054,
        "CARAGUATATUBA - UBATUBA - SAO SEBASTIAO_Mining":0.0149720302,
        "CARAGUATATUBA - UBATUBA - SAO SEBASTIAO_Manufacturing":0.0037981029,
        "CARAGUATATUBA - UBATUBA - SAO SEBASTIAO_Utilities":0.0079608361,
        "CARAGUATATUBA - UBATUBA - SAO SEBASTIAO_Construction":0.012571096,
        "CARAGUATATUBA - UBATUBA - SAO SEBASTIAO_Trade":0.031209898,
        "CARAGUATATUBA - UBATUBA - SAO SEBASTIAO_Transport":0.0416952347,
        "CARAGUATATUBA - UBATUBA - SAO SEBASTIAO_Business":0.0014748434,
        "CARAGUATATUBA - UBATUBA - SAO SEBASTIAO_Financial":0.0060216303,
        "CARAGUATATUBA - UBATUBA - SAO SEBASTIAO_RealEstate":0.0006424882,
        "CARAGUATATUBA - UBATUBA - SAO SEBASTIAO_OtherServices":0.092964573,
        "CARAGUATATUBA - UBATUBA - SAO SEBASTIAO_Government":0.0023294202,
        "RestBR_Agriculture":0.0004887316,
        "RestBR_Mining":0.0394289328,
        "RestBR_Manufacturing":0.1070964021,
        "RestBR_Utilities":0.0028467689,
        "RestBR_Construction":0.0,
        "RestBR_Trade":0.0,
        "RestBR_Transport":0.0420879023,
        "RestBR_Business":0.0024041446,
        "RestBR_Financial":0.0162201517,
        "RestBR_RealEstate":0.0007158708,
        "RestBR_OtherServices":0.0,
        "RestBR_Government":0.0025346378
    },
    "CARAGUATATUBA - UBATUBA - SAO SEBASTIAO_Manufacturing":{
        "CARAGUATATUBA - UBATUBA - SAO SEBASTIAO_Agriculture":0.0582392225,
        "CARAGUATATUBA - UBATUBA - SAO SEBASTIAO_Mining":0.042077781,
        "CARAGUATATUBA - UBATUBA - SAO SEBASTIAO_Manufacturing":0.0067515813,
        "CARAGUATATUBA - UBATUBA - SAO SEBASTIAO_Utilities":0.015455605,
        "CARAGUATATUBA - UBATUBA - SAO SEBASTIAO_Construction":0.000917125,
        "CARAGUATATUBA - UBATUBA - SAO SEBASTIAO_Trade":0.078902322,
        "CARAGUATATUBA - UBATUBA - SAO SEBASTIAO_Transport":0.049323146,
        "CARAGUATATUBA - UBATUBA - SAO SEBASTIAO_Business":0.005629733,
        "CARAGUATATUBA - UBATUBA - SAO SEBASTIAO_Financial":0.017558898,
        "CARAGUATATUBA - UBATUBA - SAO SEBASTIAO_RealEstate":0.001830843,
        "CARAGUATATUBA - UBATUBA - SAO SEBASTIAO_OtherServices":0.045851826,
        "CARAGUATATUBA - UBATUBA - SAO SEBASTIAO_Government":0.002798704,
        "RestBR_Agriculture":0.0182100305,
        "RestBR_Mining":0.0,
        "RestBR_Manufacturing":0.2663179017,
        "RestBR_Utilities":0.0,
        "RestBR_Construction":0.0,
        "RestBR_Trade":0.0,
        "RestBR_Transport":0.0,
        "RestBR_Business":0.0,
        "RestBR_Financial":0.0,
        "RestBR_RealEstate":0.0,
        "RestBR_OtherServices":0.0,
        "RestBR_Government":0.0
    },
    "CARAGUATATUBA - UBATUBA - SAO SEBASTIAO_Utilities":{
        "CARAGUATATUBA - UBATUBA - SAO SEBASTIAO_Agriculture":0.0000164134,
        "CARAGUATATUBA - UBATUBA - SAO SEBASTIAO_Mining":0.0029427127,
        "CARAGUATATUBA - UBATUBA - SAO SEBASTIAO_Manufacturing":0.0013470911,
        "CARAGUATATUBA - UBATUBA - SAO SEBASTIAO_Utilities":0.1466342569,
        "CARAGUATATUBA - UBATUBA - SAO SEBASTIAO_Construction":0.0110948912,
        "CARAGUATATUBA - UBATUBA - SAO SEBASTIAO_Trade":0.0105724642,
        "CARAGUATATUBA - UBATUBA - SAO SEBASTIAO_Transport":0.0047930421,
        "CARAGUATATUBA - UBATUBA - SAO SEBASTIAO_Business":0.0012876358,
        "CARAGUATATUBA - UBATUBA - SAO SEBASTIAO_Financial":0.0030400091,
        "CARAGUATATUBA - UBATUBA - SAO SEBASTIAO_RealEstate":0.0010513395,
        "CARAGUATATUBA - UBATUBA - SAO SEBASTIAO_OtherServices":0.0298675536,
        "CARAGUATATUBA - UBATUBA - SAO SEBASTIAO_Government":0.0011388103,
        "RestBR_Agriculture":0.0004469586,
        "RestBR_Mining":0.0119708063,
        "RestBR_Manufacturing":0.0746454579,
        "RestBR_Utilities":0.1291253111,
        "RestBR_Construction":0.0016662458,
        "RestBR_Trade":0.0095900638,
        "RestBR_Transport":0.0138154929,
        "RestBR_Business":0.0052556562,
        "RestBR_Financial":0.0186550639,
        "RestBR_RealEstate":0.0032432645,
        "RestBR_OtherServices":0.0207653724,
        "RestBR_Government":0.0034556347
    },
    "CARAGUATATUBA - UBATUBA - SAO SEBASTIAO_Construction":{
        "CARAGUATATUBA - UBATUBA - SAO SEBASTIAO_Agriculture":0.0000397513,
        "CARAGUATATUBA - UBATUBA - SAO SEBASTIAO_Mining":0.0009680001,
        "CARAGUATATUBA - UBATUBA - SAO SEBASTIAO_Manufacturing":0.0015951851,
        "CARAGUATATUBA - UBATUBA - SAO SEBASTIAO_Utilities":0.0001943806,
        "CARAGUATATUBA - UBATUBA - SAO SEBASTIAO_Construction":0.093540153,
        "CARAGUATATUBA - UBATUBA - SAO SEBASTIAO_Trade":0.0132710314,
        "CARAGUATATUBA - UBATUBA - SAO SEBASTIAO_Transport":0.0013445687,
        "CARAGUATATUBA - UBATUBA - SAO SEBASTIAO_Business":0.0001944674,
        "CARAGUATATUBA - UBATUBA - SAO SEBASTIAO_Financial":0.0008777165,
        "CARAGUATATUBA - UBATUBA - SAO SEBASTIAO_RealEstate":0.0001804032,
        "CARAGUATATUBA - UBATUBA - SAO SEBASTIAO_OtherServices":0.0060303957,
        "CARAGUATATUBA - UBATUBA - SAO SEBASTIAO_Government":0.0001274408,
        "RestBR_Agriculture":0.0025195217,
        "RestBR_Mining":0.0102197529,
        "RestBR_Manufacturing":0.2036251179,
        "RestBR_Utilities":0.0009683784,
        "RestBR_Construction":0.0,
        "RestBR_Trade":0.0444466186,
        "RestBR_Transport":0.0105601503,
        "RestBR_Business":0.0020591766,
        "RestBR_Financial":0.0134071335,
        "RestBR_RealEstate":0.0015001778,
        "RestBR_OtherServices":0.0172834753,
        "RestBR_Government":0.0010450932
    },
    "CARAGUATATUBA - UBATUBA - SAO SEBASTIAO_Trade":{
        "CARAGUATATUBA - UBATUBA - SAO SEBASTIAO_Agriculture":0.0002355907,
        "CARAGUATATUBA - UBATUBA - SAO SEBASTIAO_Mining":0.0000271181,
        "CARAGUATATUBA - UBATUBA - SAO SEBASTIAO_Manufacturing":0.0007395374,
        "CARAGUATATUBA - UBATUBA - SAO SEBASTIAO_Utilities":0.0048753807,
        "CARAGUATATUBA - UBATUBA - SAO SEBASTIAO_Construction":0.0006544397,
        "CARAGUATATUBA - UBATUBA - SAO SEBASTIAO_Trade":0.0201161946,
        "CARAGUATATUBA - UBATUBA - SAO SEBASTIAO_Transport":0.0094275438,
        "CARAGUATATUBA - UBATUBA - SAO SEBASTIAO_Business":0.0018754167,
        "CARAGUATATUBA - UBATUBA - SAO SEBASTIAO_Financial":0.0024041652,
        "CARAGUATATUBA - UBATUBA - SAO SEBASTIAO_RealEstate":0.0060183605,
        "CARAGUATATUBA - UBATUBA - SAO SEBASTIAO_OtherServices":0.0342749915,
        "CARAGUATATUBA - UBATUBA - SAO SEBASTIAO_Government":0.0007401867,
        "RestBR_Agriculture":0.0089123013,
        "RestBR_Mining":0.0001619089,
        "RestBR_Manufacturing":0.0566413066,
        "RestBR_Utilities":0.0127136873,
        "RestBR_Construction":0.0003808663,
        "RestBR_Trade":0.0073885874,
        "RestBR_Transport":0.0409146652,
        "RestBR_Business":0.0112325043,
        "RestBR_Financial":0.0211942758,
        "RestBR_RealEstate":0.0277952145,
        "RestBR_OtherServices":0.0456428045,
        "RestBR_Government":0.0033671063
    },
    "CARAGUATATUBA - UBATUBA - SAO SEBASTIAO_Transport":{
        "CARAGUATATUBA - UBATUBA - SAO SEBASTIAO_Agriculture":0.0000297962,
        "CARAGUATATUBA - UBATUBA - SAO SEBASTIAO_Mining":0.000082829,
        "CARAGUATATUBA - UBATUBA - SAO SEBASTIAO_Manufacturing":0.0047892937,
        "CARAGUATATUBA - UBATUBA - SAO SEBASTIAO_Utilities":0.0032389693,
        "CARAGUATATUBA - UBATUBA - SAO SEBASTIAO_Construction":0.003140253,
        "CARAGUATATUBA - UBATUBA - SAO SEBASTIAO_Trade":0.0364728951,
        "CARAGUATATUBA - UBATUBA - SAO SEBASTIAO_Transport":0.0404273997,
        "CARAGUATATUBA - UBATUBA - SAO SEBASTIAO_Business":0.0022258733,
        "CARAGUATATUBA - UBATUBA - SAO SEBASTIAO_Financial":0.0051389847,
        "CARAGUATATUBA - UBATUBA - SAO SEBASTIAO_RealEstate":0.0024393445,
        "CARAGUATATUBA - UBATUBA - SAO SEBASTIAO_OtherServices":0.0503541717,
        "CARAGUATATUBA - UBATUBA - SAO SEBASTIAO_Government":0.0014270112,
        "RestBR_Agriculture":0.0005385228,
        "RestBR_Mining":0.000200777,
        "RestBR_Manufacturing":0.1777456873,
        "RestBR_Utilities":0.0025009917,
        "RestBR_Construction":0.0,
        "RestBR_Trade":0.0105207989,
        "RestBR_Transport":0.0721031313,
        "RestBR_Business":0.0054160787,
        "RestBR_Financial":0.0196388953,
        "RestBR_RealEstate":0.0042928065,
        "RestBR_OtherServices":0.0073184133,
        "RestBR_Government":0.0024626308
    },
    "CARAGUATATUBA - UBATUBA - SAO SEBASTIAO_Business":{
        "CARAGUATATUBA - UBATUBA - SAO SEBASTIAO_Agriculture":0.0000164516,
        "CARAGUATATUBA - UBATUBA - SAO SEBASTIAO_Mining":0.0001103053,
        "CARAGUATATUBA - UBATUBA - SAO SEBASTIAO_Manufacturing":0.0009598258,
        "CARAGUATATUBA - UBATUBA - SAO SEBASTIAO_Utilities":0.0053470367,
        "CARAGUATATUBA - UBATUBA - SAO SEBASTIAO_Construction":0.016369376,
        "CARAGUATATUBA - UBATUBA - SAO SEBASTIAO_Trade":0.02498731,
        "CARAGUATATUBA - UBATUBA - SAO SEBASTIAO_Transport":0.0048101348,
        "CARAGUATATUBA - UBATUBA - SAO SEBASTIAO_Business":0.03319994,
        "CARAGUATATUBA - UBATUBA - SAO SEBASTIAO_Financial":0.0079041222,
        "CARAGUATATUBA - UBATUBA - SAO SEBASTIAO_RealEstate":0.0058005267,
        "CARAGUATATUBA - UBATUBA - SAO SEBASTIAO_OtherServices":0.140586594,
        "CARAGUATATUBA - UBATUBA - SAO SEBASTIAO_Government":0.0030333998,
        "RestBR_Agriculture":0.0002232864,
        "RestBR_Mining":0.0001782487,
        "RestBR_Manufacturing":0.0269890742,
        "RestBR_Utilities":0.0018925363,
        "RestBR_Construction":0.0,
        "RestBR_Trade":0.0,
        "RestBR_Transport":0.0048294082,
        "RestBR_Business":0.087757946,
        "RestBR_Financial":0.0212123088,
        "RestBR_RealEstate":0.0064300183,
        "RestBR_OtherServices":0.0,
        "RestBR_Government":0.0032835812
    },
    "CARAGUATATUBA - UBATUBA - SAO SEBASTIAO_Financial":{
        "CARAGUATATUBA - UBATUBA - SAO SEBASTIAO_Agriculture":0.0000060296,
        "CARAGUATATUBA - UBATUBA - SAO SEBASTIAO_Mining":0.0000421721,
        "CARAGUATATUBA - UBATUBA - SAO SEBASTIAO_Manufacturing":0.0004671308,
        "CARAGUATATUBA - UBATUBA - SAO SEBASTIAO_Utilities":0.004112766,
        "CARAGUATATUBA - UBATUBA - SAO SEBASTIAO_Construction":0.002982811,
        "CARAGUATATUBA - UBATUBA - SAO SEBASTIAO_Trade":0.00593415,
        "CARAGUATATUBA - UBATUBA - SAO SEBASTIAO_Transport":0.0099618117,
        "CARAGUATATUBA - UBATUBA - SAO SEBASTIAO_Business":0.0210266655,
        "CARAGUATATUBA - UBATUBA - SAO SEBASTIAO_Financial":0.024249182,
        "CARAGUATATUBA - UBATUBA - SAO SEBASTIAO_RealEstate":0.0064040656,
        "CARAGUATATUBA - UBATUBA - SAO SEBASTIAO_OtherServices":0.101801513,
        "CARAGUATATUBA - UBATUBA - SAO SEBASTIAO_Government":0.0030231526,
        "RestBR_Agriculture":0.0000565359,
        "RestBR_Mining":0.0000363828,
        "RestBR_Manufacturing":0.0092184982,
        "RestBR_Utilities":0.0,
        "RestBR_Construction":0.0,
        "RestBR_Trade":0.0,
        "RestBR_Transport":0.0042534403,
        "RestBR_Business":0.0182458725,
        "RestBR_Financial":0.099823722,
        "RestBR_RealEstate":0.0032109764,
        "RestBR_OtherServices":0.0,
        "RestBR_Government":0.0014597264
    },
    "CARAGUATATUBA - UBATUBA - SAO SEBASTIAO_RealEstate":{
        "CARAGUATATUBA - UBATUBA - SAO SEBASTIAO_Agriculture":0.0000030347,
        "CARAGUATATUBA - UBATUBA - SAO SEBASTIAO_Mining":0.0001929385,
        "CARAGUATATUBA - UBATUBA - SAO SEBASTIAO_Manufacturing":0.0002564418,
        "CARAGUATATUBA - UBATUBA - SAO SEBASTIAO_Utilities":0.0007477955,
        "CARAGUATATUBA - UBATUBA - SAO SEBASTIAO_Construction":0.002920853,
        "CARAGUATATUBA - UBATUBA - SAO SEBASTIAO_Trade":0.0026626627,
        "CARAGUATATUBA - UBATUBA - SAO SEBASTIAO_Transport":0.0003425086,
        "CARAGUATATUBA - UBATUBA - SAO SEBASTIAO_Business":0.0004350381,
        "CARAGUATATUBA - UBATUBA - SAO SEBASTIAO_Financial":0.008271448,
        "CARAGUATATUBA - UBATUBA - SAO SEBASTIAO_RealEstate":0.0009363066,
        "CARAGUATATUBA - UBATUBA - SAO SEBASTIAO_OtherServices":0.0073475175,
        "CARAGUATATUBA - UBATUBA - SAO SEBASTIAO_Government":0.0001455681,
        "RestBR_Agriculture":0.0000519778,
        "RestBR_Mining":0.0004349355,
        "RestBR_Manufacturing":0.0090328872,
        "RestBR_Utilities":0.0005117265,
        "RestBR_Construction":0.0,
        "RestBR_Trade":0.0005980033,
        "RestBR_Transport":0.0005113654,
        "RestBR_Business":0.0009845159,
        "RestBR_Financial":0.029632913,
        "RestBR_RealEstate":0.0018058474,
        "RestBR_OtherServices":0.0006507405,
        "RestBR_Government":0.0002315429
    },
    "CARAGUATATUBA - UBATUBA - SAO SEBASTIAO_OtherServices":{
        "CARAGUATATUBA - UBATUBA - SAO SEBASTIAO_Agriculture":0.0000991566,
        "CARAGUATATUBA - UBATUBA - SAO SEBASTIAO_Mining":0.0000262991,
        "CARAGUATATUBA - UBATUBA - SAO SEBASTIAO_Manufacturing":0.0008146409,
        "CARAGUATATUBA - UBATUBA - SAO SEBASTIAO_Utilities":0.0041023128,
        "CARAGUATATUBA - UBATUBA - SAO SEBASTIAO_Construction":0.0020005788,
        "CARAGUATATUBA - UBATUBA - SAO SEBASTIAO_Trade":0.010878831,
        "CARAGUATATUBA - UBATUBA - SAO SEBASTIAO_Transport":0.003048494,
        "CARAGUATATUBA - UBATUBA - SAO SEBASTIAO_Business":0.004832892,
        "CARAGUATATUBA - UBATUBA - SAO SEBASTIAO_Financial":0.0015396743,
        "CARAGUATATUBA - UBATUBA - SAO SEBASTIAO_RealEstate":0.002768554,
        "CARAGUATATUBA - UBATUBA - SAO SEBASTIAO_OtherServices":0.0743274128,
        "CARAGUATATUBA - UBATUBA - SAO SEBASTIAO_Government":0.0006670377,
        "RestBR_Agriculture":0.0042321614,
        "RestBR_Mining":0.0001799259,
        "RestBR_Manufacturing":0.0702917141,
        "RestBR_Utilities":0.0125470822,
        "RestBR_Construction":0.0015597502,
        "RestBR_Trade":0.021222212,
        "RestBR_Transport":0.015264293,
        "RestBR_Business":0.033166663,
        "RestBR_Financial":0.0154616697,
        "RestBR_RealEstate":0.014729964,
        "RestBR_OtherServices":0.0160117392,
        "RestBR_Government":0.0034968613
    },
    "CARAGUATATUBA - UBATUBA - SAO SEBASTIAO_Government":{
        "CARAGUATATUBA - UBATUBA - SAO SEBASTIAO_Agriculture":0.0000854233,
        "CARAGUATATUBA - UBATUBA - SAO SEBASTIAO_Mining":0.0000893379,
        "CARAGUATATUBA - UBATUBA - SAO SEBASTIAO_Manufacturing":0.0007061466,
        "CARAGUATATUBA - UBATUBA - SAO SEBASTIAO_Utilities":0.010118646,
        "CARAGUATATUBA - UBATUBA - SAO SEBASTIAO_Construction":0.013924249,
        "CARAGUATATUBA - UBATUBA - SAO SEBASTIAO_Trade":0.0107382091,
        "CARAGUATATUBA - UBATUBA - SAO SEBASTIAO_Transport":0.0046638958,
        "CARAGUATATUBA - UBATUBA - SAO SEBASTIAO_Business":0.0052458454,
        "CARAGUATATUBA - UBATUBA - SAO SEBASTIAO_Financial":0.0096183569,
        "CARAGUATATUBA - UBATUBA - SAO SEBASTIAO_RealEstate":0.0013574021,
        "CARAGUATATUBA - UBATUBA - SAO SEBASTIAO_OtherServices":0.0709521239,
        "CARAGUATATUBA - UBATUBA - SAO SEBASTIAO_Government":0.0011994381,
        "RestBR_Agriculture":0.0014825067,
        "RestBR_Mining":0.0002050281,
        "RestBR_Manufacturing":0.0251931984,
        "RestBR_Utilities":0.0071375,
        "RestBR_Construction":0.0,
        "RestBR_Trade":0.0025761569,
        "RestBR_Transport":0.0071086302,
        "RestBR_Business":0.0120857536,
        "RestBR_Financial":0.0350095991,
        "RestBR_RealEstate":0.0022476249,
        "RestBR_OtherServices":0.0072500181,
        "RestBR_Government":0.0022699517
    },
    "RestBR_Agriculture":{
        "CARAGUATATUBA - UBATUBA - SAO SEBASTIAO_Agriculture":0.0,
        "CARAGUATATUBA - UBATUBA - SAO SEBASTIAO_Mining":0.0000008651,
        "CARAGUATATUBA - UBATUBA - SAO SEBASTIAO_Manufacturing":0.0000100601,
        "CARAGUATATUBA - UBATUBA - SAO SEBASTIAO_Utilities":0.0000358313,
        "CARAGUATATUBA - UBATUBA - SAO SEBASTIAO_Construction":0.0000020966,
        "CARAGUATATUBA - UBATUBA - SAO SEBASTIAO_Trade":0.0001261549,
        "CARAGUATATUBA - UBATUBA - SAO SEBASTIAO_Transport":0.000020617,
        "CARAGUATATUBA - UBATUBA - SAO SEBASTIAO_Business":0.0000001577,
        "CARAGUATATUBA - UBATUBA - SAO SEBASTIAO_Financial":0.0000083908,
        "CARAGUATATUBA - UBATUBA - SAO SEBASTIAO_RealEstate":0.0000000357,
        "CARAGUATATUBA - UBATUBA - SAO SEBASTIAO_OtherServices":0.0000088326,
        "CARAGUATATUBA - UBATUBA - SAO SEBASTIAO_Government":0.0000007351,
        "RestBR_Agriculture":0.040534311,
        "RestBR_Mining":0.0011020229,
        "RestBR_Manufacturing":0.2064129699,
        "RestBR_Utilities":0.0232654107,
        "RestBR_Construction":0.0005905984,
        "RestBR_Trade":0.0592689801,
        "RestBR_Transport":0.019973012,
        "RestBR_Business":0.0002014233,
        "RestBR_Financial":0.0152450012,
        "RestBR_RealEstate":0.0000364219,
        "RestBR_OtherServices":0.0036831274,
        "RestBR_Government":0.0007406749
    },
    "RestBR_Mining":{
        "CARAGUATATUBA - UBATUBA - SAO SEBASTIAO_Agriculture":0.0,
        "CARAGUATATUBA - UBATUBA - SAO SEBASTIAO_Mining":0.0,
        "CARAGUATATUBA - UBATUBA - SAO SEBASTIAO_Manufacturing":0.0,
        "CARAGUATATUBA - UBATUBA - SAO SEBASTIAO_Utilities":0.0000094576,
        "CARAGUATATUBA - UBATUBA - SAO SEBASTIAO_Construction":0.0000361559,
        "CARAGUATATUBA - UBATUBA - SAO SEBASTIAO_Trade":0.0000456204,
        "CARAGUATATUBA - UBATUBA - SAO SEBASTIAO_Transport":0.0000308481,
        "CARAGUATATUBA - UBATUBA - SAO SEBASTIAO_Business":0.0000004618,
        "CARAGUATATUBA - UBATUBA - SAO SEBASTIAO_Financial":0.0,
        "CARAGUATATUBA - UBATUBA - SAO SEBASTIAO_RealEstate":0.000000429,
        "CARAGUATATUBA - UBATUBA - SAO SEBASTIAO_OtherServices":0.0001608561,
        "CARAGUATATUBA - UBATUBA - SAO SEBASTIAO_Government":0.0000015974,
        "RestBR_Agriculture":0.000524637,
        "RestBR_Mining":0.054400963,
        "RestBR_Manufacturing":0.110894505,
        "RestBR_Utilities":0.0107981474,
        "RestBR_Construction":0.0125349401,
        "RestBR_Trade":0.0311642776,
        "RestBR_Transport":0.0837522889,
        "RestBR_Business":0.0038785262,
        "RestBR_Financial":0.022241782,
        "RestBR_RealEstate":0.00135793,
        "RestBR_OtherServices":0.0928037169,
        "RestBR_Government":0.0048624606
    },
    "RestBR_Manufacturing":{
        "CARAGUATATUBA - UBATUBA - SAO SEBASTIAO_Agriculture":0.0000148078,
        "CARAGUATATUBA - UBATUBA - SAO SEBASTIAO_Mining":0.0000360523,
        "CARAGUATATUBA - UBATUBA - SAO SEBASTIAO_Manufacturing":0.0,
        "CARAGUATATUBA - UBATUBA - SAO SEBASTIAO_Utilities":0.0000248853,
        "CARAGUATATUBA - UBATUBA - SAO SEBASTIAO_Construction":0.0000033105,
        "CARAGUATATUBA - UBATUBA - SAO SEBASTIAO_Trade":0.0001732951,
        "CARAGUATATUBA - UBATUBA - SAO SEBASTIAO_Transport":0.0000544326,
        "CARAGUATATUBA - UBATUBA - SAO SEBASTIAO_Business":0.0000048113,
        "CARAGUATATUBA - UBATUBA - SAO SEBASTIAO_Financial":0.0000109311,
        "CARAGUATATUBA - UBATUBA - SAO SEBASTIAO_RealEstate":0.0000019248,
        "CARAGUATATUBA - UBATUBA - SAO SEBASTIAO_OtherServices":0.0001130107,
        "CARAGUATATUBA - UBATUBA - SAO SEBASTIAO_Government":0.0000029774,
        "RestBR_Agriculture":0.0764344452,
        "RestBR_Mining":0.0420417287,
        "RestBR_Manufacturing":0.273069483,
        "RestBR_Utilities":0.0154307197,
        "RestBR_Construction":0.0009138145,
        "RestBR_Trade":0.0787290269,
        "RestBR_Transport":0.0492687134,
        "RestBR_Business":0.0056249217,
        "RestBR_Financial":0.0175479669,
        "RestBR_RealEstate":0.0018289182,
        "RestBR_OtherServices":0.0457388153,
        "RestBR_Government":0.0027957266
    },
    "RestBR_Utilities":{
        "CARAGUATATUBA - UBATUBA - SAO SEBASTIAO_Agriculture":0.0,
        "CARAGUATATUBA - UBATUBA - SAO SEBASTIAO_Mining":0.0,
        "CARAGUATATUBA - UBATUBA - SAO SEBASTIAO_Manufacturing":0.0,
        "CARAGUATATUBA - UBATUBA - SAO SEBASTIAO_Utilities":0.0001554326,
        "CARAGUATATUBA - UBATUBA - SAO SEBASTIAO_Construction":0.0000271015,
        "CARAGUATATUBA - UBATUBA - SAO SEBASTIAO_Trade":0.0000142811,
        "CARAGUATATUBA - UBATUBA - SAO SEBASTIAO_Transport":0.0,
        "CARAGUATATUBA - UBATUBA - SAO SEBASTIAO_Business":0.0,
        "CARAGUATATUBA - UBATUBA - SAO SEBASTIAO_Financial":0.0,
        "CARAGUATATUBA - UBATUBA - SAO SEBASTIAO_RealEstate":0.0,
        "CARAGUATATUBA - UBATUBA - SAO SEBASTIAO_OtherServices":0.0000494718,
        "CARAGUATATUBA - UBATUBA - SAO SEBASTIAO_Government":0.0,
        "RestBR_Agriculture":0.000463372,
        "RestBR_Mining":0.014913519,
        "RestBR_Manufacturing":0.075992549,
        "RestBR_Utilities":0.2756041354,
        "RestBR_Construction":0.0127340355,
        "RestBR_Trade":0.0201482469,
        "RestBR_Transport":0.018608535,
        "RestBR_Business":0.006543292,
        "RestBR_Financial":0.021695073,
        "RestBR_RealEstate":0.004294604,
        "RestBR_OtherServices":0.0505834542,
        "RestBR_Government":0.004594445
    },
    "RestBR_Construction":{
        "CARAGUATATUBA - UBATUBA - SAO SEBASTIAO_Agriculture":0.0,
        "CARAGUATATUBA - UBATUBA - SAO SEBASTIAO_Mining":0.0,
        "CARAGUATATUBA - UBATUBA - SAO SEBASTIAO_Manufacturing":0.0,
        "CARAGUATATUBA - UBATUBA - SAO SEBASTIAO_Utilities":0.0,
        "CARAGUATATUBA - UBATUBA - SAO SEBASTIAO_Construction":0.0002399584,
        "CARAGUATATUBA - UBATUBA - SAO SEBASTIAO_Trade":0.0,
        "CARAGUATATUBA - UBATUBA - SAO SEBASTIAO_Transport":0.0,
        "CARAGUATATUBA - UBATUBA - SAO SEBASTIAO_Business":0.0,
        "CARAGUATATUBA - UBATUBA - SAO SEBASTIAO_Financial":0.0,
        "CARAGUATATUBA - UBATUBA - SAO SEBASTIAO_RealEstate":0.0,
        "CARAGUATATUBA - UBATUBA - SAO SEBASTIAO_OtherServices":0.0,
        "CARAGUATATUBA - UBATUBA - SAO SEBASTIAO_Government":0.0,
        "RestBR_Agriculture":0.002559273,
        "RestBR_Mining":0.011187753,
        "RestBR_Manufacturing":0.205220303,
        "RestBR_Utilities":0.001162759,
        "RestBR_Construction":0.0933001946,
        "RestBR_Trade":0.05771765,
        "RestBR_Transport":0.011904719,
        "RestBR_Business":0.002253644,
        "RestBR_Financial":0.01428485,
        "RestBR_RealEstate":0.001680581,
        "RestBR_OtherServices":0.023313871,
        "RestBR_Government":0.001172534
    },
    "RestBR_Trade":{
        "CARAGUATATUBA - UBATUBA - SAO SEBASTIAO_Agriculture":0.0,
        "CARAGUATATUBA - UBATUBA - SAO SEBASTIAO_Mining":0.0,
        "CARAGUATATUBA - UBATUBA - SAO SEBASTIAO_Manufacturing":0.0,
        "CARAGUATATUBA - UBATUBA - SAO SEBASTIAO_Utilities":0.0,
        "CARAGUATATUBA - UBATUBA - SAO SEBASTIAO_Construction":0.0000015918,
        "CARAGUATATUBA - UBATUBA - SAO SEBASTIAO_Trade":0.0000316436,
        "CARAGUATATUBA - UBATUBA - SAO SEBASTIAO_Transport":0.0,
        "CARAGUATATUBA - UBATUBA - SAO SEBASTIAO_Business":0.0,
        "CARAGUATATUBA - UBATUBA - SAO SEBASTIAO_Financial":0.0,
        "CARAGUATATUBA - UBATUBA - SAO SEBASTIAO_RealEstate":0.0,
        "CARAGUATATUBA - UBATUBA - SAO SEBASTIAO_OtherServices":0.0000311795,
        "CARAGUATATUBA - UBATUBA - SAO SEBASTIAO_Government":0.0,
        "RestBR_Agriculture":0.009147892,
        "RestBR_Mining":0.000189027,
        "RestBR_Manufacturing":0.057380844,
        "RestBR_Utilities":0.017589068,
        "RestBR_Construction":0.0010337142,
        "RestBR_Trade":0.0274731384,
        "RestBR_Transport":0.050342209,
        "RestBR_Business":0.013107921,
        "RestBR_Financial":0.023598441,
        "RestBR_RealEstate":0.033813575,
        "RestBR_OtherServices":0.0798866165,
        "RestBR_Government":0.004107293
    },
    "RestBR_Transport":{
        "CARAGUATATUBA - UBATUBA - SAO SEBASTIAO_Agriculture":0.0,
        "CARAGUATATUBA - UBATUBA - SAO SEBASTIAO_Mining":0.0,
        "CARAGUATATUBA - UBATUBA - SAO SEBASTIAO_Manufacturing":0.0,
        "CARAGUATATUBA - UBATUBA - SAO SEBASTIAO_Utilities":0.0000036061,
        "CARAGUATATUBA - UBATUBA - SAO SEBASTIAO_Construction":0.0000082581,
        "CARAGUATATUBA - UBATUBA - SAO SEBASTIAO_Trade":0.0000570985,
        "CARAGUATATUBA - UBATUBA - SAO SEBASTIAO_Transport":0.0000063688,
        "CARAGUATATUBA - UBATUBA - SAO SEBASTIAO_Business":0.0,
        "CARAGUATATUBA - UBATUBA - SAO SEBASTIAO_Financial":0.0,
        "CARAGUATATUBA - UBATUBA - SAO SEBASTIAO_RealEstate":0.0000004637,
        "CARAGUATATUBA - UBATUBA - SAO SEBASTIAO_OtherServices":0.0000855664,
        "CARAGUATATUBA - UBATUBA - SAO SEBASTIAO_Government":0.0000003167,
        "RestBR_Agriculture":0.000568319,
        "RestBR_Mining":0.000283606,
        "RestBR_Manufacturing":0.182534981,
        "RestBR_Utilities":0.0057363549,
        "RestBR_Construction":0.0031319949,
        "RestBR_Trade":0.0469365955,
        "RestBR_Transport":0.1125241622,
        "RestBR_Business":0.007641952,
        "RestBR_Financial":0.02477788,
        "RestBR_RealEstate":0.0067316873,
        "RestBR_OtherServices":0.0575870186,
        "RestBR_Government":0.0038893253
    },
    "RestBR_Business":{
        "CARAGUATATUBA - UBATUBA - SAO SEBASTIAO_Agriculture":0.0,
        "CARAGUATATUBA - UBATUBA - SAO SEBASTIAO_Mining":0.0000000356,
        "CARAGUATATUBA - UBATUBA - SAO SEBASTIAO_Manufacturing":0.0,
        "CARAGUATATUBA - UBATUBA - SAO SEBASTIAO_Utilities":0.000006351,
        "CARAGUATATUBA - UBATUBA - SAO SEBASTIAO_Construction":0.0000471157,
        "CARAGUATATUBA - UBATUBA - SAO SEBASTIAO_Trade":0.000036579,
        "CARAGUATATUBA - UBATUBA - SAO SEBASTIAO_Transport":0.0000035702,
        "CARAGUATATUBA - UBATUBA - SAO SEBASTIAO_Business":0.0,
        "CARAGUATATUBA - UBATUBA - SAO SEBASTIAO_Financial":0.0,
        "CARAGUATATUBA - UBATUBA - SAO SEBASTIAO_RealEstate":0.0000038897,
        "CARAGUATATUBA - UBATUBA - SAO SEBASTIAO_OtherServices":0.0002435619,
        "CARAGUATATUBA - UBATUBA - SAO SEBASTIAO_Government":0.0000020883,
        "RestBR_Agriculture":0.000239738,
        "RestBR_Mining":0.0002885184,
        "RestBR_Manufacturing":0.0279489,
        "RestBR_Utilities":0.007233222,
        "RestBR_Construction":0.0163222603,
        "RestBR_Trade":0.024950731,
        "RestBR_Transport":0.0096359728,
        "RestBR_Business":0.120957886,
        "RestBR_Financial":0.029116431,
        "RestBR_RealEstate":0.0122266553,
        "RestBR_OtherServices":0.1403430321,
        "RestBR_Government":0.0063148927
    },
    "RestBR_Financial":{
        "CARAGUATATUBA - UBATUBA - SAO SEBASTIAO_Agriculture":0.0,
        "CARAGUATATUBA - UBATUBA - SAO SEBASTIAO_Mining":0.0000000279,
        "CARAGUATATUBA - UBATUBA - SAO SEBASTIAO_Manufacturing":0.0,
        "CARAGUATATUBA - UBATUBA - SAO SEBASTIAO_Utilities":0.0000045622,
        "CARAGUATATUBA - UBATUBA - SAO SEBASTIAO_Construction":0.0000092761,
        "CARAGUATATUBA - UBATUBA - SAO SEBASTIAO_Trade":0.0000100631,
        "CARAGUATATUBA - UBATUBA - SAO SEBASTIAO_Transport":0.0000085648,
        "CARAGUATATUBA - UBATUBA - SAO SEBASTIAO_Business":0.0000138796,
        "CARAGUATATUBA - UBATUBA - SAO SEBASTIAO_Financial":0.0,
        "CARAGUATATUBA - UBATUBA - SAO SEBASTIAO_RealEstate":0.0000052901,
        "CARAGUATATUBA - UBATUBA - SAO SEBASTIAO_OtherServices":0.0001999681,
        "CARAGUATATUBA - UBATUBA - SAO SEBASTIAO_Government":0.0000025227,
        "RestBR_Agriculture":0.0000625655,
        "RestBR_Mining":0.000078527,
        "RestBR_Manufacturing":0.009685629,
        "RestBR_Utilities":0.0041082038,
        "RestBR_Construction":0.0029735349,
        "RestBR_Trade":0.0059240869,
        "RestBR_Transport":0.0142066872,
        "RestBR_Business":0.0392586584,
        "RestBR_Financial":0.124072904,
        "RestBR_RealEstate":0.0096097519,
        "RestBR_OtherServices":0.1016015449,
        "RestBR_Government":0.0044803563
    },
    "RestBR_RealEstate":{
        "CARAGUATATUBA - UBATUBA - SAO SEBASTIAO_Agriculture":0.0,
        "CARAGUATATUBA - UBATUBA - SAO SEBASTIAO_Mining":0.0,
        "CARAGUATATUBA - UBATUBA - SAO SEBASTIAO_Manufacturing":0.0,
        "CARAGUATATUBA - UBATUBA - SAO SEBASTIAO_Utilities":0.0000008572,
        "CARAGUATATUBA - UBATUBA - SAO SEBASTIAO_Construction":0.0000078336,
        "CARAGUATATUBA - UBATUBA - SAO SEBASTIAO_Trade":0.0000041323,
        "CARAGUATATUBA - UBATUBA - SAO SEBASTIAO_Transport":0.0000001482,
        "CARAGUATATUBA - UBATUBA - SAO SEBASTIAO_Business":0.0,
        "CARAGUATATUBA - UBATUBA - SAO SEBASTIAO_Financial":0.0,
        "CARAGUATATUBA - UBATUBA - SAO SEBASTIAO_RealEstate":0.0000000116,
        "CARAGUATATUBA - UBATUBA - SAO SEBASTIAO_OtherServices":0.0000122848,
        "CARAGUATATUBA - UBATUBA - SAO SEBASTIAO_Government":0.0000000504,
        "RestBR_Agriculture":0.0000550125,
        "RestBR_Mining":0.000627874,
        "RestBR_Manufacturing":0.009289329,
        "RestBR_Utilities":0.0012586648,
        "RestBR_Construction":0.0029130194,
        "RestBR_Trade":0.0032565337,
        "RestBR_Transport":0.0008537258,
        "RestBR_Business":0.001419554,
        "RestBR_Financial":0.037904361,
        "RestBR_RealEstate":0.0027421424,
        "RestBR_OtherServices":0.0079859732,
        "RestBR_Government":0.0003770606
    },
    "RestBR_OtherServices":{
        "CARAGUATATUBA - UBATUBA - SAO SEBASTIAO_Agriculture":0.0,
        "CARAGUATATUBA - UBATUBA - SAO SEBASTIAO_Mining":0.0,
        "CARAGUATATUBA - UBATUBA - SAO SEBASTIAO_Manufacturing":0.0,
        "CARAGUATATUBA - UBATUBA - SAO SEBASTIAO_Utilities":0.0,
        "CARAGUATATUBA - UBATUBA - SAO SEBASTIAO_Construction":0.0000045176,
        "CARAGUATATUBA - UBATUBA - SAO SEBASTIAO_Trade":0.0,
        "CARAGUATATUBA - UBATUBA - SAO SEBASTIAO_Transport":0.0,
        "CARAGUATATUBA - UBATUBA - SAO SEBASTIAO_Business":0.0,
        "CARAGUATATUBA - UBATUBA - SAO SEBASTIAO_Financial":0.0,
        "CARAGUATATUBA - UBATUBA - SAO SEBASTIAO_RealEstate":0.0,
        "CARAGUATATUBA - UBATUBA - SAO SEBASTIAO_OtherServices":0.0001282025,
        "CARAGUATATUBA - UBATUBA - SAO SEBASTIAO_Government":0.0,
        "RestBR_Agriculture":0.004331318,
        "RestBR_Mining":0.000206225,
        "RestBR_Manufacturing":0.071106355,
        "RestBR_Utilities":0.016649395,
        "RestBR_Construction":0.0035558114,
        "RestBR_Trade":0.032101043,
        "RestBR_Transport":0.018312787,
        "RestBR_Business":0.037999555,
        "RestBR_Financial":0.017001344,
        "RestBR_RealEstate":0.017498518,
        "RestBR_OtherServices":0.0902109495,
        "RestBR_Government":0.004163899
    },
    "RestBR_Government":{
        "CARAGUATATUBA - UBATUBA - SAO SEBASTIAO_Agriculture":0.0,
        "CARAGUATATUBA - UBATUBA - SAO SEBASTIAO_Mining":0.0,
        "CARAGUATATUBA - UBATUBA - SAO SEBASTIAO_Manufacturing":0.0,
        "CARAGUATATUBA - UBATUBA - SAO SEBASTIAO_Utilities":0.0000115273,
        "CARAGUATATUBA - UBATUBA - SAO SEBASTIAO_Construction":0.0000371701,
        "CARAGUATATUBA - UBATUBA - SAO SEBASTIAO_Trade":0.0000167065,
        "CARAGUATATUBA - UBATUBA - SAO SEBASTIAO_Transport":0.0000018955,
        "CARAGUATATUBA - UBATUBA - SAO SEBASTIAO_Business":0.0,
        "CARAGUATATUBA - UBATUBA - SAO SEBASTIAO_Financial":0.0,
        "CARAGUATATUBA - UBATUBA - SAO SEBASTIAO_RealEstate":0.0000003917,
        "CARAGUATATUBA - UBATUBA - SAO SEBASTIAO_OtherServices":0.0001191327,
        "CARAGUATATUBA - UBATUBA - SAO SEBASTIAO_Government":0.0000000583,
        "RestBR_Agriculture":0.00156793,
        "RestBR_Mining":0.000294366,
        "RestBR_Manufacturing":0.025899345,
        "RestBR_Utilities":0.0172446187,
        "RestBR_Construction":0.0138870789,
        "RestBR_Trade":0.0132976595,
        "RestBR_Transport":0.0117706305,
        "RestBR_Business":0.017331599,
        "RestBR_Financial":0.044627956,
        "RestBR_RealEstate":0.0036046353,
        "RestBR_OtherServices":0.0780830093,
        "RestBR_Government":0.0034693315
    }
}