{
    "PATOS_Agriculture":{
        "PATOS_Agriculture":0.0036311795,
        "PATOS_Mining":0.000416436,
        "PATOS_Manufacturing":0.1190246498,
        "PATOS_Utilities":0.0,
        "PATOS_Construction":0.0003172174,
        "PATOS_Trade":0.059395135,
        "PATOS_Transport":0.0116628118,
        "PATOS_Business":0.0000789436,
        "PATOS_Financial":0.015253392,
        "PATOS_RealEstate":0.000019494,
        "PATOS_OtherServices":0.0027333004,
        "PATOS_Government":0.0006450398,
        "RestBR_Agriculture":0.0369031315,
        "RestBR_Mining":0.000686452,
        "RestBR_Manufacturing":0.0873983802,
        "RestBR_Utilities":0.023301242,
        "RestBR_Construction":0.0002754776,
        "RestBR_Trade":0.0,
        "RestBR_Transport":0.0083308172,
        "RestBR_Business":0.0001226374,
        "RestBR_Financial":0.0,
        "RestBR_RealEstate":0.0000169636,
        "RestBR_OtherServices":0.0009586596,
        "RestBR_Government":0.0000963702
    },
    "PATOS_Mining":{
        "PATOS_Agriculture":0.000102723,
        "PATOS_Mining":0.006767615,
        "PATOS_Manufacturing":0.0460452311,
        "PATOS_Utilities":0.0,
        "PATOS_Construction":0.0048450101,
        "PATOS_Trade":0.031209898,
        "PATOS_Transport":0.0351936348,
        "PATOS_Business":0.0010939107,
        "PATOS_Financial":0.022241782,
        "PATOS_RealEstate":0.0005230257,
        "PATOS_OtherServices":0.0495614184,
        "PATOS_Government":0.0030473525,
        "RestBR_Agriculture":0.000421914,
        "RestBR_Mining":0.047633348,
        "RestBR_Manufacturing":0.0648492739,
        "RestBR_Utilities":0.010807605,
        "RestBR_Construction":0.0077260859,
        "RestBR_Trade":0.0,
        "RestBR_Transport":0.0485895022,
        "RestBR_Business":0.0027850773,
        "RestBR_Financial":0.0,
        "RestBR_RealEstate":0.0008353333,
        "RestBR_OtherServices":0.0434031546,
        "RestBR_Government":0.0018167055
    },
    "PATOS_Manufacturing":{
        "PATOS_Agriculture":0.0098021194,
        "PATOS_Mining":0.0074921024,
        "PATOS_Manufacturing":0.0518757159,
        "PATOS_Utilities":0.0,
        "PATOS_Construction":0.0002314665,
        "PATOS_Trade":0.0582370741,
        "PATOS_Transport":0.0135673928,
        "PATOS_Business":0.0010396552,
        "PATOS_Financial":0.0115357812,
        "PATOS_RealEstate":0.0004616339,
        "PATOS_OtherServices":0.0160074077,
        "PATOS_Government":0.0011482039,
        "RestBR_Agriculture":0.0666471336,
        "RestBR_Mining":0.0345856786,
        "RestBR_Manufacturing":0.2211937671,
        "RestBR_Utilities":0.015455605,
        "RestBR_Construction":0.0006856585,
        "RestBR_Trade":0.0206652479,
        "RestBR_Transport":0.0357557532,
        "RestBR_Business":0.0045900778,
        "RestBR_Financial":0.0060231168,
        "RestBR_RealEstate":0.0013692091,
        "RestBR_OtherServices":0.0298444183,
        "RestBR_Government":0.0016505001
    },
    "PATOS_Utilities":{
        "PATOS_Agriculture":0.000463372,
        "PATOS_Mining":0.014913519,
        "PATOS_Manufacturing":0.075992549,
        "PATOS_Utilities":0.0,
        "PATOS_Construction":0.012761137,
        "PATOS_Trade":0.020162528,
        "PATOS_Transport":0.018608535,
        "PATOS_Business":0.006543292,
        "PATOS_Financial":0.021695073,
        "PATOS_RealEstate":0.004294604,
        "PATOS_OtherServices":0.050632926,
        "PATOS_Government":0.004594445,
        "RestBR_Agriculture":0.0,
        "RestBR_Mining":0.0,
        "RestBR_Manufacturing":0.0,
        "RestBR_Utilities":0.275759568,
        "RestBR_Construction":0.0,
        "RestBR_Trade":0.0,
        "RestBR_Transport":0.0,
        "RestBR_Business":0.0,
        "RestBR_Financial":0.0,
        "RestBR_RealEstate":0.0,
        "RestBR_OtherServices":0.0,
        "RestBR_Government":0.0
    },
    "PATOS_Construction":{
        "PATOS_Agriculture":0.000353522,
        "PATOS_Mining":0.0021460846,
        "PATOS_Manufacturing":0.0601154589,
        "PATOS_Utilities":0.0,
        "PATOS_Construction":0.0164943772,
        "PATOS_Trade":0.0458956465,
        "PATOS_Transport":0.003527913,
        "PATOS_Business":0.0004483735,
        "PATOS_Financial":0.0101106372,
        "PATOS_RealEstate":0.0004565192,
        "PATOS_OtherServices":0.0087686321,
        "PATOS_Government":0.0005182515,
        "RestBR_Agriculture":0.002205751,
        "RestBR_Mining":0.0090416684,
        "RestBR_Manufacturing":0.1451048441,
        "RestBR_Utilities":0.001162759,
        "RestBR_Construction":0.0770457758,
        "RestBR_Trade":0.0118220035,
        "RestBR_Transport":0.008376806,
        "RestBR_Business":0.0018052705,
        "RestBR_Financial":0.0041742128,
        "RestBR_RealEstate":0.0012240618,
        "RestBR_OtherServices":0.0145452389,
        "RestBR_Government":0.0006542825
    },
    "PATOS_Trade":{
        "PATOS_Agriculture":0.0004320866,
        "PATOS_Mining":0.0000123987,
        "PATOS_Manufacturing":0.0057475489,
        "PATOS_Utilities":0.0,
        "PATOS_Construction":0.0000962568,
        "PATOS_Trade":0.014183916,
        "PATOS_Transport":0.0051013003,
        "PATOS_Business":0.0008917402,
        "PATOS_Financial":0.0057113143,
        "PATOS_RealEstate":0.0031408026,
        "PATOS_OtherServices":0.0102780532,
        "PATOS_Government":0.0006207557,
        "RestBR_Agriculture":0.0087158054,
        "RestBR_Mining":0.0001766283,
        "RestBR_Manufacturing":0.0516332951,
        "RestBR_Utilities":0.017589068,
        "RestBR_Construction":0.0009390492,
        "RestBR_Trade":0.013320866,
        "RestBR_Transport":0.0452409087,
        "RestBR_Business":0.0122161808,
        "RestBR_Financial":0.0178871267,
        "RestBR_RealEstate":0.0306727724,
        "RestBR_OtherServices":0.0696397428,
        "RestBR_Government":0.0034865373
    },
    "PATOS_Transport":{
        "PATOS_Agriculture":0.0000720288,
        "PATOS_Mining":0.0000499153,
        "PATOS_Manufacturing":0.0490598238,
        "PATOS_Utilities":0.0,
        "PATOS_Construction":0.0007834142,
        "PATOS_Trade":0.0342859726,
        "PATOS_Transport":0.0216268953,
        "PATOS_Business":0.001394996,
        "PATOS_Financial":0.0160909255,
        "PATOS_RealEstate":0.0016779056,
        "PATOS_OtherServices":0.0199021921,
        "PATOS_Government":0.0015773891,
        "RestBR_Agriculture":0.0004962902,
        "RestBR_Mining":0.0002336907,
        "RestBR_Manufacturing":0.1334751572,
        "RestBR_Utilities":0.005739961,
        "RestBR_Construction":0.0023568388,
        "RestBR_Trade":0.0127077214,
        "RestBR_Transport":0.0909036357,
        "RestBR_Business":0.006246956,
        "RestBR_Financial":0.0086869545,
        "RestBR_RealEstate":0.0050542454,
        "RestBR_OtherServices":0.0377703929,
        "RestBR_Government":0.0023122529
    },
    "PATOS_Business":{
        "PATOS_Agriculture":0.0000452579,
        "PATOS_Mining":0.0000756466,
        "PATOS_Manufacturing":0.0111889333,
        "PATOS_Utilities":0.0,
        "PATOS_Construction":0.0060827925,
        "PATOS_Trade":0.02498731,
        "PATOS_Transport":0.0039040312,
        "PATOS_Business":0.0156068017,
        "PATOS_Financial":0.0281643092,
        "PATOS_RealEstate":0.0045404989,
        "PATOS_OtherServices":0.0722635829,
        "PATOS_Government":0.0038157758,
        "RestBR_Agriculture":0.0001944801,
        "RestBR_Mining":0.0002129074,
        "RestBR_Manufacturing":0.0167599667,
        "RestBR_Utilities":0.007239573,
        "RestBR_Construction":0.0102865835,
        "RestBR_Trade":0.0,
        "RestBR_Transport":0.0057355118,
        "RestBR_Business":0.1053510843,
        "RestBR_Financial":0.0009521218,
        "RestBR_RealEstate":0.0076900461,
        "RestBR_OtherServices":0.0683230111,
        "RestBR_Government":0.0025012052
    },
    "PATOS_Financial":{
        "PATOS_Agriculture":0.0000033201,
        "PATOS_Mining":0.0000057888,
        "PATOS_Manufacturing":0.0010899425,
        "PATOS_Utilities":0.0,
        "PATOS_Construction":0.0003115648,
        "PATOS_Trade":0.0018127223,
        "PATOS_Transport":0.0016183155,
        "PATOS_Business":0.0030016048,
        "PATOS_Financial":0.0569514626,
        "PATOS_RealEstate":0.0010033691,
        "PATOS_OtherServices":0.0147089477,
        "PATOS_Government":0.0007611707,
        "RestBR_Agriculture":0.0000592454,
        "RestBR_Mining":0.0000727661,
        "RestBR_Manufacturing":0.0085956865,
        "RestBR_Utilities":0.004112766,
        "RestBR_Construction":0.0026712462,
        "RestBR_Trade":0.0041214277,
        "RestBR_Transport":0.0125969365,
        "RestBR_Business":0.0362709332,
        "RestBR_Financial":0.0671214414,
        "RestBR_RealEstate":0.0086116729,
        "RestBR_OtherServices":0.0870925653,
        "RestBR_Government":0.0037217083
    },
    "PATOS_RealEstate":{
        "PATOS_Agriculture":0.0000076063,
        "PATOS_Mining":0.0001205562,
        "PATOS_Manufacturing":0.0027237252,
        "PATOS_Utilities":0.0,
        "PATOS_Construction":0.0007949422,
        "PATOS_Trade":0.0025952684,
        "PATOS_Transport":0.0002532828,
        "PATOS_Business":0.000282696,
        "PATOS_Financial":0.0268537617,
        "PATOS_RealEstate":0.0004830772,
        "PATOS_OtherServices":0.0030111055,
        "PATOS_Government":0.000166839,
        "RestBR_Agriculture":0.0000474062,
        "RestBR_Mining":0.0005073178,
        "RestBR_Manufacturing":0.0065656038,
        "RestBR_Utilities":0.001259522,
        "RestBR_Construction":0.0021259108,
        "RestBR_Trade":0.0006653976,
        "RestBR_Transport":0.0006005912,
        "RestBR_Business":0.001136858,
        "RestBR_Financial":0.0110505993,
        "RestBR_RealEstate":0.0022590768,
        "RestBR_OtherServices":0.0049871525,
        "RestBR_Government":0.000210272
    },
    "PATOS_OtherServices":{
        "PATOS_Agriculture":0.000432529,
        "PATOS_Mining":0.0000285983,
        "PATOS_Manufacturing":0.0150580784,
        "PATOS_Utilities":0.0,
        "PATOS_Construction":0.0006998391,
        "PATOS_Trade":0.018453438,
        "PATOS_Transport":0.0039232723,
        "PATOS_Business":0.0054654816,
        "PATOS_Financial":0.0086992416,
        "PATOS_RealEstate":0.0034363406,
        "PATOS_OtherServices":0.0220352794,
        "PATOS_Government":0.001330487,
        "RestBR_Agriculture":0.003898789,
        "RestBR_Mining":0.0001776267,
        "RestBR_Manufacturing":0.0560482766,
        "RestBR_Utilities":0.016649395,
        "RestBR_Construction":0.0028604899,
        "RestBR_Trade":0.013647605,
        "RestBR_Transport":0.0143895147,
        "RestBR_Business":0.0325340734,
        "RestBR_Financial":0.0083021024,
        "RestBR_RealEstate":0.0140621774,
        "RestBR_OtherServices":0.0683038726,
        "RestBR_Government":0.002833412
    },
    "PATOS_Government":{
        "PATOS_Agriculture":0.0001332368,
        "PATOS_Mining":0.0000347368,
        "PATOS_Manufacturing":0.004667155,
        "PATOS_Utilities":0.0,
        "PATOS_Construction":0.0023290678,
        "PATOS_Trade":0.006512998,
        "PATOS_Transport":0.0021461792,
        "PATOS_Business":0.0021212452,
        "PATOS_Financial":0.0194315497,
        "PATOS_RealEstate":0.0006024289,
        "PATOS_OtherServices":0.0180939634,
        "PATOS_Government":0.0009944738,
        "RestBR_Agriculture":0.0014346932,
        "RestBR_Mining":0.0002596292,
        "RestBR_Manufacturing":0.02123219,
        "RestBR_Utilities":0.017256146,
        "RestBR_Construction":0.0115951812,
        "RestBR_Trade":0.006801368,
        "RestBR_Transport":0.0096263468,
        "RestBR_Business":0.0152103538,
        "RestBR_Financial":0.0251964063,
        "RestBR_RealEstate":0.0030025981,
        "RestBR_OtherServices":0.0601081786,
        "RestBR_Government":0.002474916
    },
    "RestBR_Agriculture":{
        "PATOS_Agriculture":0.0,
        "PATOS_Mining":0.0000000306,
        "PATOS_Manufacturing":0.0000115861,
        "PATOS_Utilities":0.0,
        "PATOS_Construction":0.0000000298,
        "PATOS_Trade":0.0000116986,
        "PATOS_Transport":0.0000011413,
        "PATOS_Business":0.000000006,
        "PATOS_Financial":0.0000026306,
        "PATOS_RealEstate":0.0000000018,
        "PATOS_OtherServices":0.0000002933,
        "PATOS_Government":0.0000000726,
        "RestBR_Agriculture":0.040534311,
        "RestBR_Mining":0.0011028574,
        "RestBR_Manufacturing":0.2064114439,
        "RestBR_Utilities":0.023301242,
        "RestBR_Construction":0.0005926652,
        "RestBR_Trade":0.0593834364,
        "RestBR_Transport":0.0199924877,
        "RestBR_Business":0.000201575,
        "RestBR_Financial":0.0152507614,
        "RestBR_RealEstate":0.0000364558,
        "RestBR_OtherServices":0.0036916667,
        "RestBR_Government":0.0007413374
    },
    "RestBR_Mining":{
        "PATOS_Agriculture":0.0,
        "PATOS_Mining":0.0,
        "PATOS_Manufacturing":0.0000045548,
        "PATOS_Utilities":0.0,
        "PATOS_Construction":0.0000004422,
        "PATOS_Trade":0.0000056774,
        "PATOS_Transport":0.0000035215,
        "PATOS_Business":0.0000000571,
        "PATOS_Financial":0.000003501,
        "PATOS_RealEstate":0.0000000477,
        "PATOS_OtherServices":0.0000059868,
        "PATOS_Government":0.0000004031,
        "RestBR_Agriculture":0.000524637,
        "RestBR_Mining":0.054400963,
        "RestBR_Manufacturing":0.1108899502,
        "RestBR_Utilities":0.010807605,
        "RestBR_Construction":0.0125706538,
        "RestBR_Trade":0.0312042206,
        "RestBR_Transport":0.0837796155,
        "RestBR_Business":0.0038789309,
        "RestBR_Financial":0.022238281,
        "RestBR_RealEstate":0.0013583113,
        "RestBR_OtherServices":0.0929585862,
        "RestBR_Government":0.0048636549
    },
    "RestBR_Manufacturing":{
        "PATOS_Agriculture":0.0,
        "PATOS_Mining":0.0,
        "PATOS_Manufacturing":0.0,
        "PATOS_Utilities":0.0,
        "PATOS_Construction":0.0000000063,
        "PATOS_Trade":0.0000121164,
        "PATOS_Transport":0.0000006747,
        "PATOS_Business":0.0,
        "PATOS_Financial":0.0000022661,
        "PATOS_RealEstate":0.0000000124,
        "PATOS_OtherServices":0.0000016528,
        "PATOS_Government":0.0000001526,
        "RestBR_Agriculture":0.076449253,
        "RestBR_Mining":0.042077781,
        "RestBR_Manufacturing":0.273069483,
        "RestBR_Utilities":0.015455605,
        "RestBR_Construction":0.0009171187,
        "RestBR_Trade":0.0788902056,
        "RestBR_Transport":0.0493224713,
        "RestBR_Business":0.005629733,
        "RestBR_Financial":0.0175566319,
        "RestBR_RealEstate":0.0018308306,
        "RestBR_OtherServices":0.0458501732,
        "RestBR_Government":0.0027985514
    },
    "RestBR_Utilities":{
        "PATOS_Agriculture":0.0000000238,
        "PATOS_Mining":0.0000009919,
        "PATOS_Manufacturing":0.0000072086,
        "PATOS_Utilities":0.0,
        "PATOS_Construction":0.0000011353,
        "PATOS_Trade":0.0000047521,
        "PATOS_Transport":0.000001783,
        "PATOS_Business":0.0000004483,
        "PATOS_Financial":0.0000045817,
        "PATOS_RealEstate":0.0000003817,
        "PATOS_OtherServices":0.0000059839,
        "PATOS_Government":0.0000006279,
        "RestBR_Agriculture":0.0004633482,
        "RestBR_Mining":0.0149125271,
        "RestBR_Manufacturing":0.0759853404,
        "RestBR_Utilities":0.275759568,
        "RestBR_Construction":0.0127600017,
        "RestBR_Trade":0.0201577759,
        "RestBR_Transport":0.018606752,
        "RestBR_Business":0.0065428437,
        "RestBR_Financial":0.0216904913,
        "RestBR_RealEstate":0.0042942223,
        "RestBR_OtherServices":0.0506269421,
        "RestBR_Government":0.0045938171
    },
    "RestBR_Construction":{
        "PATOS_Agriculture":0.0,
        "PATOS_Mining":0.0,
        "PATOS_Manufacturing":0.0000038209,
        "PATOS_Utilities":0.0,
        "PATOS_Construction":0.0,
        "PATOS_Trade":0.0000092035,
        "PATOS_Transport":0.000000233,
        "PATOS_Business":0.0,
        "PATOS_Financial":0.0000019278,
        "PATOS_RealEstate":0.0000000213,
        "PATOS_OtherServices":0.0000009779,
        "PATOS_Government":0.0000000708,
        "RestBR_Agriculture":0.002559273,
        "RestBR_Mining":0.011187753,
        "RestBR_Manufacturing":0.2052164821,
        "RestBR_Utilities":0.001162759,
        "RestBR_Construction":0.093540153,
        "RestBR_Trade":0.0577084465,
        "RestBR_Transport":0.011904486,
        "RestBR_Business":0.002253644,
        "RestBR_Financial":0.0142829222,
        "RestBR_RealEstate":0.0016805597,
        "RestBR_OtherServices":0.0233128931,
        "RestBR_Government":0.0011724632
    },
    "RestBR_Trade":{
        "PATOS_Agriculture":0.0,
        "PATOS_Mining":0.0,
        "PATOS_Manufacturing":0.0,
        "PATOS_Utilities":0.0,
        "PATOS_Construction":0.0,
        "PATOS_Trade":0.0000032494,
        "PATOS_Transport":0.0,
        "PATOS_Business":0.0,
        "PATOS_Financial":0.0,
        "PATOS_RealEstate":0.0,
        "PATOS_OtherServices":0.0,
        "PATOS_Government":0.0,
        "RestBR_Agriculture":0.009147892,
        "RestBR_Mining":0.000189027,
        "RestBR_Manufacturing":0.057380844,
        "RestBR_Utilities":0.017589068,
        "RestBR_Construction":0.001035306,
        "RestBR_Trade":0.0275015326,
        "RestBR_Transport":0.050342209,
        "RestBR_Business":0.013107921,
        "RestBR_Financial":0.023598441,
        "RestBR_RealEstate":0.033813575,
        "RestBR_OtherServices":0.079917796,
        "RestBR_Government":0.004107293
    },
    "RestBR_Transport":{
        "PATOS_Agriculture":0.0,
        "PATOS_Mining":0.0,
        "PATOS_Manufacturing":0.0000021473,
        "PATOS_Utilities":0.0,
        "PATOS_Construction":0.0000000184,
        "PATOS_Trade":0.0000071714,
        "PATOS_Transport":0.0,
        "PATOS_Business":0.0,
        "PATOS_Financial":0.000003174,
        "PATOS_RealEstate":0.000000039,
        "PATOS_OtherServices":0.0000020237,
        "PATOS_Government":0.0000002083,
        "RestBR_Agriculture":0.000568319,
        "RestBR_Mining":0.000283606,
        "RestBR_Manufacturing":0.1825328337,
        "RestBR_Utilities":0.005739961,
        "RestBR_Construction":0.0031402346,
        "RestBR_Trade":0.0469865226,
        "RestBR_Transport":0.112530531,
        "RestBR_Business":0.007641952,
        "RestBR_Financial":0.024774706,
        "RestBR_RealEstate":0.006732112,
        "RestBR_OtherServices":0.0576705613,
        "RestBR_Government":0.0038894337
    },
    "RestBR_Business":{
        "PATOS_Agriculture":0.0,
        "PATOS_Mining":0.0000000031,
        "PATOS_Manufacturing":0.0000010921,
        "PATOS_Utilities":0.0,
        "PATOS_Construction":0.0000005431,
        "PATOS_Trade":0.0000044955,
        "PATOS_Transport":0.0000003859,
        "PATOS_Business":0.0,
        "PATOS_Financial":0.0000045248,
        "PATOS_RealEstate":0.0000004049,
        "PATOS_OtherServices":0.0000087724,
        "PATOS_Government":0.0000005109,
        "RestBR_Agriculture":0.000239738,
        "RestBR_Mining":0.0002885509,
        "RestBR_Manufacturing":0.0279478079,
        "RestBR_Utilities":0.007239573,
        "RestBR_Construction":0.0163688329,
        "RestBR_Trade":0.0249828145,
        "RestBR_Transport":0.0096391571,
        "RestBR_Business":0.120957886,
        "RestBR_Financial":0.0291119062,
        "RestBR_RealEstate":0.0122301401,
        "RestBR_OtherServices":0.1405778216,
        "RestBR_Government":0.0063164701
    },
    "RestBR_Financial":{
        "PATOS_Agriculture":0.0,
        "PATOS_Mining":0.0,
        "PATOS_Manufacturing":0.0,
        "PATOS_Utilities":0.0,
        "PATOS_Construction":0.0,
        "PATOS_Trade":0.0000002209,
        "PATOS_Transport":0.0,
        "PATOS_Business":0.0,
        "PATOS_Financial":0.0000116173,
        "PATOS_RealEstate":0.0,
        "PATOS_OtherServices":0.0,
        "PATOS_Government":0.0,
        "RestBR_Agriculture":0.0000625655,
        "RestBR_Mining":0.0000785549,
        "RestBR_Manufacturing":0.009685629,
        "RestBR_Utilities":0.004112766,
        "RestBR_Construction":0.002982811,
        "RestBR_Trade":0.0059339291,
        "RestBR_Transport":0.014215252,
        "RestBR_Business":0.039272538,
        "RestBR_Financial":0.1240612867,
        "RestBR_RealEstate":0.009615042,
        "RestBR_OtherServices":0.101801513,
        "RestBR_Government":0.004482879
    },
    "RestBR_RealEstate":{
        "PATOS_Agriculture":0.0,
        "PATOS_Mining":0.0,
        "PATOS_Manufacturing":0.0000001736,
        "PATOS_Utilities":0.0,
        "PATOS_Construction":0.0000000374,
        "PATOS_Trade":0.0000005202,
        "PATOS_Transport":0.0000000168,
        "PATOS_Business":0.0,
        "PATOS_Financial":0.000005118,
        "PATOS_RealEstate":0.0,
        "PATOS_OtherServices":0.0000003361,
        "PATOS_Government":0.0000000228,
        "RestBR_Agriculture":0.0000550125,
        "RestBR_Mining":0.000627874,
        "RestBR_Manufacturing":0.0092891554,
        "RestBR_Utilities":0.001259522,
        "RestBR_Construction":0.0029208156,
        "RestBR_Trade":0.0032601458,
        "RestBR_Transport":0.0008538572,
        "RestBR_Business":0.001419554,
        "RestBR_Financial":0.037899243,
        "RestBR_RealEstate":0.002742154,
        "RestBR_OtherServices":0.0079979219,
        "RestBR_Government":0.0003770882
    },
    "RestBR_OtherServices":{
        "PATOS_Agriculture":0.0,
        "PATOS_Mining":0.0,
        "PATOS_Manufacturing":0.0,
        "PATOS_Utilities":0.0,
        "PATOS_Construction":0.0,
        "PATOS_Trade":0.0000041808,
        "PATOS_Transport":0.0,
        "PATOS_Business":0.0,
        "PATOS_Financial":0.0000017976,
        "PATOS_RealEstate":0.0,
        "PATOS_OtherServices":0.000000056,
        "PATOS_Government":0.0000001299,
        "RestBR_Agriculture":0.004331318,
        "RestBR_Mining":0.000206225,
        "RestBR_Manufacturing":0.071106355,
        "RestBR_Utilities":0.016649395,
        "RestBR_Construction":0.003560329,
        "RestBR_Trade":0.0320968622,
        "RestBR_Transport":0.018312787,
        "RestBR_Business":0.037999555,
        "RestBR_Financial":0.0169995464,
        "RestBR_RealEstate":0.017498518,
        "RestBR_OtherServices":0.090339096,
        "RestBR_Government":0.0041637691
    },
    "RestBR_Government":{
        "PATOS_Agriculture":0.0,
        "PATOS_Mining":0.0,
        "PATOS_Manufacturing":0.0,
        "PATOS_Utilities":0.0,
        "PATOS_Construction":0.0,
        "PATOS_Trade":0.0000014881,
        "PATOS_Transport":0.0,
        "PATOS_Business":0.0,
        "PATOS_Financial":0.0000038942,
        "PATOS_RealEstate":0.0,
        "PATOS_OtherServices":0.0,
        "PATOS_Government":0.0000000662,
        "RestBR_Agriculture":0.00156793,
        "RestBR_Mining":0.000294366,
        "RestBR_Manufacturing":0.025899345,
        "RestBR_Utilities":0.017256146,
        "RestBR_Construction":0.013924249,
        "RestBR_Trade":0.0133128779,
        "RestBR_Transport":0.011772526,
        "RestBR_Business":0.017331599,
        "RestBR_Financial":0.0446240618,
        "RestBR_RealEstate":0.003605027,
        "RestBR_OtherServices":0.078202142,
        "RestBR_Government":0.0034693236
    }
}